{
  "project_info": {
    "project_number": "586187531218",
    "project_id": "my-application-4ea39",
    "storage_bucket": "my-application-4ea39.appspot.com"
  },
  "client": [
    {
      "client_info": {
        "mobilesdk_app_id": "1:586187531218:android:0e536794a133a57b365e0b",
        "android_client_info": {
          "package_name": "com.example.myapplication"
        }
      },
      "oauth_client": [],
      "api_key": [
        {
          "current_key": "AIzaSyBesEUBJMOceraABWnbzr7WYXk0qichKNM"
        }
      ],
      "services": {
        "appinvite_service": {
          "other_platform_oauth_client": []
        }
      }
    }
  ],
  "configuration_version": "1"
}